equinox/__init__.py
equinox/_ad.py
equinox/_caches.py
equinox/_callback.py
equinox/_compile_utils.py
equinox/_config.py
equinox/_custom_types.py
equinox/_deprecate.py
equinox/_doc_utils.py
equinox/_enum.py
equinox/_errors.py
equinox/_eval_shape.py
equinox/_filters.py
equinox/_jit.py
equinox/_make_jaxpr.py
equinox/_misc.py
equinox/_pretty_print.py
equinox/_serialisation.py
equinox/_sharding.py
equinox/_tree.py
equinox/_unvmap.py
equinox/_update.py
equinox/_vmap_pmap.py
equinox/py.typed
equinox/_module/README.md
equinox/_module/__init__.py
equinox/_module/_better_abstract.py
equinox/_module/_field.py
equinox/_module/_module.py
equinox/_module/_prebuilt.py
equinox/debug/__init__.py
equinox/debug/_announce_transform.py
equinox/debug/_backward_nan.py
equinox/debug/_breakpoint_if.py
equinox/debug/_dce.py
equinox/debug/_max_traces.py
equinox/internal/README.md
equinox/internal/__init__.py
equinox/internal/_closure_to_pytree.py
equinox/internal/_finalise_jaxpr.py
equinox/internal/_getkey.py
equinox/internal/_misc.py
equinox/internal/_nextafter.py
equinox/internal/_noinline.py
equinox/internal/_nontraceable.py
equinox/internal/_omega.py
equinox/internal/_onnx.py
equinox/internal/_primitive.py
equinox/internal/_str2jax.py
equinox/internal/_loop/__init__.py
equinox/internal/_loop/bounded.py
equinox/internal/_loop/checkpointed.py
equinox/internal/_loop/common.py
equinox/internal/_loop/loop.py
equinox/nn/__init__.py
equinox/nn/_activations.py
equinox/nn/_attention.py
equinox/nn/_batch_norm.py
equinox/nn/_conv.py
equinox/nn/_dropout.py
equinox/nn/_embedding.py
equinox/nn/_inference.py
equinox/nn/_linear.py
equinox/nn/_misc.py
equinox/nn/_mlp.py
equinox/nn/_normalisation.py
equinox/nn/_pool.py
equinox/nn/_rnn.py
equinox/nn/_sequential.py
equinox/nn/_shared.py
equinox/nn/_spectral_norm.py
equinox/nn/_stateful.py
equinox/nn/_weight_norm.py
equinox-0.13.2.dist-info/METADATA
equinox-0.13.2.dist-info/WHEEL
equinox-0.13.2.dist-info/licenses/LICENSE
equinox-0.13.2.dist-info/RECORD
